{
  "viewBox": {
    "width": 375,
    "height": 3741.2334
  },
  "anchors": [
    {
      "id": "anchor_read_001",
      "type": "read",
      "index": 1,
      "x": 199.656,
      "y": 172.2513
    },
    {
      "id": "anchor_quiz_001",
      "type": "quiz",
      "index": 1,
      "x": 267.1925,
      "y": 361.7761
    },
    {
      "id": "anchor_read_002",
      "type": "read",
      "index": 2,
      "x": 163.9925,
      "y": 551.301
    },
    {
      "id": "anchor_quiz_002",
      "type": "quiz",
      "index": 2,
      "x": 108.5916,
      "y": 740.8259
    },
    {
      "id": "anchor_read_003",
      "type": "read",
      "index": 3,
      "x": 199.656,
      "y": 930.3508
    },
    {
      "id": "anchor_quiz_003",
      "type": "quiz",
      "index": 3,
      "x": 276.9041,
      "y": 1119.8756
    },
    {
      "id": "anchor_read_004",
      "type": "read",
      "index": 4,
      "x": 173.9925,
      "y": 1309.4005
    },
    {
      "id": "anchor_quiz_004",
      "type": "quiz",
      "index": 4,
      "x": 108.7231,
      "y": 1498.9254
    },
    {
      "id": "anchor_read_005",
      "type": "read",
      "index": 5,
      "x": 199.656,
      "y": 1688.4503
    },
    {
      "id": "anchor_quiz_005",
      "type": "quiz",
      "index": 5,
      "x": 277.1925,
      "y": 1877.9751
    },
    {
      "id": "anchor_read_006",
      "type": "read",
      "index": 6,
      "x": 98.0384,
      "y": 2067.5
    },
    {
      "id": "anchor_quiz_006",
      "type": "quiz",
      "index": 6,
      "x": 165.2535,
      "y": 2257.0249
    },
    {
      "id": "anchor_read_007",
      "type": "read",
      "index": 7,
      "x": 276.9041,
      "y": 2446.5498
    },
    {
      "id": "anchor_quiz_007",
      "type": "quiz",
      "index": 7,
      "x": 165.2535,
      "y": 2636.0747
    },
    {
      "id": "anchor_read_008",
      "type": "read",
      "index": 8,
      "x": 98.5916,
      "y": 2825.5995
    },
    {
      "id": "anchor_quiz_008",
      "type": "quiz",
      "index": 8,
      "x": 163.9925,
      "y": 3015.1244
    },
    {
      "id": "anchor_read_009",
      "type": "read",
      "index": 9,
      "x": 317.2407,
      "y": 3204.6493
    },
    {
      "id": "anchor_quiz_009",
      "type": "quiz",
      "index": 9,
      "x": 108.0384,
      "y": 3394.1742
    },
    {
      "id": "anchor_quiz_010",
      "type": "quiz",
      "index": 10,
      "x": 190.4838,
      "y": 3583.699
    }
  ]
}
